pymdp/__init__.py
pymdp/agent.py
pymdp/control.py
pymdp/default_models.py
pymdp/inference.py
pymdp/learning.py
pymdp/maths.py
pymdp/utils.py
pymdp/algos/__init__.py
pymdp/algos/fpi.py
pymdp/algos/mmp.py
pymdp/algos/mmp_old.py
pymdp/envs/__init__.py
pymdp/envs/env.py
pymdp/envs/grid_worlds.py
pymdp/envs/tmaze.py
pymdp/envs/visual_foraging.py
inferactively_pymdp-0.0.7.1.dist-info/LICENSE
inferactively_pymdp-0.0.7.1.dist-info/METADATA
inferactively_pymdp-0.0.7.1.dist-info/WHEEL
inferactively_pymdp-0.0.7.1.dist-info/top_level.txt
inferactively_pymdp-0.0.7.1.dist-info/RECORD
